eic_rucio_policy_package/__init__.py
eic_rucio_policy_package/lfn2pfn.py
eic_rucio_policy_package/non_deterministic_pfn.py
eic_rucio_policy_package/permission.py
eic_rucio_policy_package/schema.py
eic_rucio_policy_package/scope.py
eic_rucio_policy_package-0.1.1.dist-info/licenses/LICENSE
eic_rucio_policy_package-0.1.1.dist-info/METADATA
eic_rucio_policy_package-0.1.1.dist-info/WHEEL
eic_rucio_policy_package-0.1.1.dist-info/top_level.txt
eic_rucio_policy_package-0.1.1.dist-info/RECORD
