Metadata-Version: 2.4
Name: eic-rucio-policy-package
Version: 0.1.1
Summary: Rucio policy package for the EIC collaboration
Author-email: EIC <panta@jlab.org>
License:                                  Apache License
Classifier: Programming Language :: Python :: 3
Classifier: Operating System :: OS Independent
Requires-Python: >=3.9
License-File: LICENSE
Dynamic: license-file
